{"nodes": [{"id": "risk", "label": "risk.rs", "file_type": "code", "source_file": "crates/core/src/traits/risk.rs", "source_location": "L1"}, {"id": "risk_riskcheck", "label": "RiskCheck", "file_type": "code", "source_file": "crates/core/src/traits/risk.rs", "source_location": "L9"}], "edges": [{"source": "risk", "target": "riskrejection", "relation": "imports_from", "confidence": "EXTRACTED", "source_file": "crates/core/src/traits/risk.rs", "source_location": "L5", "weight": 1.0}, {"source": "risk", "target": "position", "relation": "imports_from", "confidence": "EXTRACTED", "source_file": "crates/core/src/traits/risk.rs", "source_location": "L6", "weight": 1.0}, {"source": "risk", "target": "action", "relation": "imports_from", "confidence": "EXTRACTED", "source_file": "crates/core/src/traits/risk.rs", "source_location": "L7", "weight": 1.0}, {"source": "risk", "target": "risk_riskcheck", "relation": "contains", "confidence": "EXTRACTED", "source_file": "crates/core/src/traits/risk.rs", "source_location": "L9", "weight": 1.0}]}